{
	"song": {
		"player1": "staticbf",
		"player2": "fnaf",
		"notes": [
			{
				"lengthInSteps": 16,
				"sectionNotes": [
					[
						0,
						3,
						0,
						"No Animation"
					],
					[
						0,
						2,
						0,
						"No Animation"
					],
					[
						0,
						1,
						0,
						"No Animation"
					],
					[
						0,
						0,
						0,
						"No Animation"
					]
				],
				"mustHitSection": false
			},
			{
				"lengthInSteps": 16,
				"sectionNotes": [],
				"mustHitSection": false
			},
			{
				"lengthInSteps": 16,
				"sectionNotes": [],
				"mustHitSection": false
			},
			{
				"lengthInSteps": 16,
				"sectionNotes": [],
				"mustHitSection": false
			},
			{
				"lengthInSteps": 16,
				"sectionNotes": [],
				"mustHitSection": false
			},
			{
				"lengthInSteps": 16,
				"sectionNotes": [],
				"mustHitSection": false
			},
			{
				"lengthInSteps": 16,
				"sectionNotes": [],
				"mustHitSection": false
			},
			{
				"lengthInSteps": 16,
				"sectionNotes": [],
				"mustHitSection": false
			},
			{
				"lengthInSteps": 16,
				"sectionNotes": [],
				"mustHitSection": false
			},
			{
				"lengthInSteps": 16,
				"sectionNotes": [],
				"mustHitSection": false
			},
			{
				"lengthInSteps": 16,
				"sectionNotes": [],
				"mustHitSection": false
			},
			{
				"lengthInSteps": 16,
				"sectionNotes": [],
				"mustHitSection": false
			},
			{
				"lengthInSteps": 16,
				"sectionNotes": [],
				"mustHitSection": false
			},
			{
				"lengthInSteps": 16,
				"sectionNotes": [],
				"mustHitSection": false
			},
			{
				"lengthInSteps": 16,
				"sectionNotes": [],
				"mustHitSection": false
			},
			{
				"lengthInSteps": 16,
				"sectionNotes": [],
				"mustHitSection": false
			},
			{
				"lengthInSteps": 16,
				"sectionNotes": [],
				"mustHitSection": false
			},
			{
				"lengthInSteps": 16,
				"sectionNotes": [],
				"mustHitSection": false
			},
			{
				"lengthInSteps": 16,
				"sectionNotes": [],
				"mustHitSection": false
			},
			{
				"lengthInSteps": 16,
				"sectionNotes": [],
				"mustHitSection": false
			},
			{
				"lengthInSteps": 16,
				"sectionNotes": [],
				"mustHitSection": false
			},
			{
				"lengthInSteps": 16,
				"sectionNotes": [],
				"mustHitSection": false
			},
			{
				"lengthInSteps": 16,
				"sectionNotes": [],
				"mustHitSection": false
			},
			{
				"lengthInSteps": 16,
				"sectionNotes": [],
				"mustHitSection": false
			},
			{
				"lengthInSteps": 16,
				"sectionNotes": [
					[
						41290.3225806452,
						1,
						1375
					],
					[
						42790.3225806452,
						0,
						375
					]
				],
				"changeBPM": true,
				"mustHitSection": false,
				"bpm": 120
			},
			{
				"lengthInSteps": 16,
				"sectionNotes": [
					[
						43290.3225806452,
						1,
						750
					],
					[
						43290.3225806452,
						3,
						875
					],
					[
						44290.3225806452,
						2,
						875
					]
				],
				"mustHitSection": false
			},
			{
				"lengthInSteps": 16,
				"sectionNotes": [
					[
						45290.3225806452,
						0,
						1375
					]
				],
				"mustHitSection": false
			},
			{
				"lengthInSteps": 16,
				"sectionNotes": [
					[
						47290.3225806452,
						2,
						750
					],
					[
						47290.3225806452,
						3,
						875
					],
					[
						48290.3225806452,
						1,
						750
					],
					[
						48290.3225806452,
						0,
						875
					]
				],
				"mustHitSection": false
			},
			{
				"lengthInSteps": 16,
				"sectionNotes": [
					[
						49290.3225806452,
						6,
						1375
					],
					[
						50790.3225806452,
						4,
						375
					]
				],
				"mustHitSection": false
			},
			{
				"lengthInSteps": 16,
				"sectionNotes": [
					[
						51290.3225806452,
						6,
						0
					],
					[
						51352.8225806452,
						7,
						750
					],
					[
						52290.3225806452,
						4,
						875
					]
				],
				"mustHitSection": false
			},
			{
				"lengthInSteps": 16,
				"sectionNotes": [
					[
						53290.3225806452,
						5,
						1625
					],
					[
						53290.3225806452,
						6,
						1375
					]
				],
				"mustHitSection": false
			},
			{
				"lengthInSteps": 16,
				"sectionNotes": [
					[
						55290.3225806452,
						6,
						750
					],
					[
						55290.3225806452,
						7,
						875
					],
					[
						56290.3225806452,
						5,
						750
					],
					[
						56290.3225806452,
						4,
						875
					]
				],
				"mustHitSection": false
			},
			{
				"lengthInSteps": 16,
				"sectionNotes": [
					[
						57290.3225806452,
						6,
						875
					],
					[
						58290.3225806452,
						0,
						875
					],
					[
						58290.3225806452,
						1,
						875
					],
					[
						58290.3225806452,
						2,
						875
					],
					[
						58290.3225806452,
						3,
						875
					]
				],
				"mustHitSection": false
			},
			{
				"lengthInSteps": 16,
				"sectionNotes": [
					[
						59290.3225806452,
						1,
						0
					],
					[
						59540.3225806452,
						1,
						0
					],
					[
						59446.5725806452,
						2,
						0
					],
					[
						59696.5725806452,
						3,
						0
					],
					[
						59790.3225806452,
						0,
						189
					],
					[
						60040.3225806452,
						1,
						189
					]
				],
				"changeBPM": true,
				"mustHitSection": false,
				"bpm": 240
			},
			{
				"lengthInSteps": 16,
				"sectionNotes": [
					[
						60290.3225806452,
						2,
						0
					],
					[
						60415.3225806452,
						1,
						315
					],
					[
						61123.6559139785,
						1,
						0
					],
					[
						61206.9892473118,
						3,
						0
					],
					[
						60790.3225806452,
						3,
						189
					],
					[
						61040.3225806452,
						2,
						0
					]
				],
				"mustHitSection": false
			},
			{
				"lengthInSteps": 16,
				"sectionNotes": [
					[
						61290.3225806452,
						2,
						441
					],
					[
						61790.3225806452,
						0,
						441
					]
				],
				"mustHitSection": false
			},
			{
				"lengthInSteps": 16,
				"sectionNotes": [
					[
						62290.3225806452,
						2,
						441
					],
					[
						62790.3225806452,
						3,
						441
					]
				],
				"mustHitSection": false
			},
			{
				"lengthInSteps": 16,
				"sectionNotes": [
					[
						63290.3225806452,
						1,
						0
					],
					[
						63540.3225806452,
						1,
						0
					],
					[
						63352.8225806452,
						0,
						0
					],
					[
						63415.3225806452,
						2,
						0
					],
					[
						63790.3225806452,
						3,
						0
					],
					[
						63696.5725806452,
						2,
						0
					],
					[
						64040.3225806452,
						0,
						0
					],
					[
						63946.5725806452,
						1,
						0
					],
					[
						64196.5725806452,
						1,
						0
					]
				],
				"mustHitSection": false
			},
			{
				"lengthInSteps": 16,
				"sectionNotes": [
					[
						64290.3225806452,
						2,
						0
					],
					[
						64540.3225806452,
						2,
						0
					],
					[
						64446.5725806452,
						3,
						0
					],
					[
						64790.3225806452,
						0,
						442
					],
					[
						64696.5725806452,
						3,
						0
					]
				],
				"mustHitSection": false
			},
			{
				"lengthInSteps": 16,
				"sectionNotes": [
					[
						65290.3225806452,
						2,
						0
					],
					[
						65415.3225806452,
						3,
						0
					],
					[
						65352.8225806452,
						1,
						0
					],
					[
						65540.3225806452,
						0,
						0
					],
					[
						65790.3225806452,
						3,
						0
					],
					[
						65696.5725806452,
						2,
						0
					],
					[
						66040.3225806452,
						0,
						0
					],
					[
						65946.5725806452,
						1,
						0
					],
					[
						66196.5725806452,
						2,
						0
					]
				],
				"mustHitSection": false
			},
			{
				"lengthInSteps": 16,
				"sectionNotes": [
					[
						66290.3225806452,
						1,
						0
					],
					[
						66540.3225806452,
						1,
						0
					],
					[
						66446.5725806452,
						0,
						0
					],
					[
						66790.3225806452,
						2,
						189
					],
					[
						66696.5725806452,
						3,
						0
					],
					[
						67040.3225806452,
						0,
						189
					]
				],
				"mustHitSection": false
			},
			{
				"lengthInSteps": 16,
				"sectionNotes": [
					[
						67540.3225806452,
						4,
						189
					],
					[
						67790.3225806452,
						5,
						0
					],
					[
						67915.3225806452,
						5,
						0
					],
					[
						68040.3225806452,
						6,
						189
					],
					[
						67290.3225806452,
						7,
						189
					]
				],
				"mustHitSection": false
			},
			{
				"sectionBeats": 4,
				"sectionNotes": [
					[
						68446.5725806452,
						5,
						0
					],
					[
						68290.3225806452,
						4,
						0
					],
					[
						68540.3225806452,
						6,
						0
					],
					[
						68696.5725806452,
						5,
						0
					],
					[
						68790.3225806452,
						4,
						0
					],
					[
						68946.5725806452,
						6,
						0
					],
					[
						69040.3225806452,
						7,
						0
					],
					[
						69196.5725806452,
						5,
						0
					]
				],
				"typeOfSection": 0,
				"gfSection": false,
				"altAnim": false,
				"mustHitSection": false,
				"changeBPM": false,
				"bpm": 160
			},
			{
				"sectionBeats": 4,
				"sectionNotes": [
					[
						69290.3225806452,
						6,
						189
					],
					[
						69540.3225806452,
						7,
						0
					],
					[
						69790.3225806452,
						5,
						189
					],
					[
						69696.5725806452,
						4,
						0
					],
					[
						70040.3225806452,
						7,
						0
					],
					[
						70196.5725806452,
						6,
						0
					]
				],
				"typeOfSection": 0,
				"gfSection": false,
				"altAnim": false,
				"mustHitSection": false,
				"changeBPM": false,
				"bpm": 160
			},
			{
				"sectionBeats": 4,
				"sectionNotes": [
					[
						70290.3225806452,
						4,
						189
					],
					[
						70540.3225806452,
						5,
						0
					],
					[
						70790.3225806452,
						6,
						441
					],
					[
						70696.5725806452,
						7,
						0
					]
				],
				"typeOfSection": 0,
				"gfSection": false,
				"altAnim": false,
				"mustHitSection": false,
				"changeBPM": false,
				"bpm": 160
			},
			{
				"sectionBeats": 4,
				"sectionNotes": [
					[
						71290.3225806452,
						4,
						191
					],
					[
						71540.3225806452,
						5,
						0
					],
					[
						71790.3225806452,
						6,
						126
					],
					[
						72040.3225806452,
						5,
						189
					],
					[
						71602.8225806452,
						6,
						0
					],
					[
						71665.3225806452,
						4,
						0
					],
					[
						71727.8225806452,
						7,
						0
					]
				],
				"typeOfSection": 0,
				"gfSection": false,
				"altAnim": false,
				"mustHitSection": false,
				"changeBPM": false,
				"bpm": 160
			},
			{
				"sectionBeats": 4,
				"sectionNotes": [
					[
						72290.3225806452,
						6,
						378
					],
					[
						72290.3225806452,
						7,
						441
					],
					[
						72790.3225806452,
						5,
						189
					],
					[
						73040.3225806452,
						4,
						189
					]
				],
				"typeOfSection": 0,
				"gfSection": false,
				"altAnim": false,
				"mustHitSection": false,
				"changeBPM": false,
				"bpm": 160
			},
			{
				"sectionBeats": 4,
				"sectionNotes": [
					[
						73290.3225806452,
						6,
						189
					],
					[
						73540.3225806452,
						7,
						0
					],
					[
						73540.3225806452,
						5,
						0
					],
					[
						73665.3225806452,
						4,
						0
					],
					[
						73790.3225806452,
						6,
						189
					],
					[
						74040.3225806452,
						7,
						0
					],
					[
						74165.3225806452,
						6,
						0
					]
				],
				"typeOfSection": 0,
				"gfSection": false,
				"altAnim": false,
				"mustHitSection": false,
				"changeBPM": false,
				"bpm": 160
			},
			{
				"sectionBeats": 4,
				"sectionNotes": [
					[
						74290.3225806452,
						4,
						441
					],
					[
						74790.3225806452,
						6,
						189
					],
					[
						75040.3225806452,
						5,
						189
					]
				],
				"typeOfSection": 0,
				"gfSection": false,
				"altAnim": false,
				"mustHitSection": false,
				"changeBPM": false,
				"bpm": 160
			},
			{
				"sectionBeats": 4,
				"sectionNotes": [
					[
						75290.3225806452,
						6,
						1386
					],
					[
						75290.3225806452,
						4,
						1261
					],
					[
						75290.3225806452,
						0,
						693
					],
					[
						75290.3225806452,
						2,
						630
					],
					[
						76040.3225806452,
						1,
						0
					],
					[
						76196.5725806452,
						3,
						0
					]
				],
				"typeOfSection": 0,
				"gfSection": false,
				"altAnim": false,
				"mustHitSection": false,
				"changeBPM": false,
				"bpm": 160
			},
			{
				"sectionBeats": 4,
				"sectionNotes": [
					[
						76290.3225806452,
						2,
						0
					],
					[
						76540.3225806452,
						2,
						0
					],
					[
						76446.5725806452,
						0,
						0
					],
					[
						76696.5725806452,
						1,
						0
					],
					[
						76790.3225806452,
						3,
						0
					],
					[
						77040.3225806452,
						1,
						0
					],
					[
						76946.5725806452,
						0,
						0
					],
					[
						77196.5725806452,
						3,
						0
					]
				],
				"typeOfSection": 0,
				"gfSection": false,
				"altAnim": false,
				"mustHitSection": false,
				"changeBPM": false,
				"bpm": 160
			},
			{
				"sectionBeats": 4,
				"sectionNotes": [
					[
						77290.3225806452,
						2,
						441
					],
					[
						77790.3225806452,
						0,
						0
					],
					[
						77946.5725806452,
						1,
						0
					],
					[
						78227.8225806452,
						1,
						0
					],
					[
						78040.3225806452,
						3,
						0
					],
					[
						78165.3225806452,
						2,
						0
					]
				],
				"typeOfSection": 0,
				"gfSection": false,
				"altAnim": false,
				"mustHitSection": false,
				"changeBPM": false,
				"bpm": 160
			},
			{
				"sectionBeats": 4,
				"sectionNotes": [
					[
						78290.3225806452,
						0,
						441
					],
					[
						78790.3225806452,
						2,
						441
					]
				],
				"typeOfSection": 0,
				"gfSection": false,
				"altAnim": false,
				"mustHitSection": false,
				"changeBPM": false,
				"bpm": 160
			},
			{
				"sectionBeats": 4,
				"sectionNotes": [
					[
						79290.3225806452,
						3,
						0
					],
					[
						79415.3225806452,
						2,
						190
					],
					[
						79790.3225806452,
						0,
						0
					],
					[
						79696.5725806452,
						1,
						0
					],
					[
						80040.3225806452,
						1,
						0
					],
					[
						79946.5725806452,
						2,
						0
					],
					[
						80196.5725806452,
						0,
						0
					]
				],
				"typeOfSection": 0,
				"gfSection": false,
				"altAnim": false,
				"mustHitSection": false,
				"changeBPM": false,
				"bpm": 160
			},
			{
				"sectionBeats": 4,
				"sectionNotes": [
					[
						80540.3225806452,
						2,
						0
					],
					[
						80790.3225806452,
						2,
						442
					],
					[
						80290.3225806452,
						1,
						0
					],
					[
						80446.5725806452,
						3,
						0
					],
					[
						80696.5725806452,
						1,
						0
					],
					[
						80790.3225806452,
						3,
						379
					]
				],
				"typeOfSection": 0,
				"gfSection": false,
				"altAnim": false,
				"mustHitSection": false,
				"changeBPM": false,
				"bpm": 160
			},
			{
				"sectionBeats": 4,
				"sectionNotes": [
					[
						81290.3225806452,
						0,
						189
					],
					[
						81540.3225806452,
						3,
						0
					],
					[
						81790.3225806452,
						3,
						0
					],
					[
						81696.5725806452,
						2,
						0
					],
					[
						82040.3225806452,
						0,
						0
					],
					[
						81946.5725806452,
						1,
						0
					],
					[
						82196.5725806452,
						2,
						0
					]
				],
				"typeOfSection": 0,
				"gfSection": false,
				"altAnim": false,
				"mustHitSection": false,
				"changeBPM": false,
				"bpm": 160
			},
			{
				"sectionBeats": 4,
				"sectionNotes": [
					[
						82290.3225806452,
						1,
						441
					],
					[
						82290.3225806452,
						3,
						379
					],
					[
						82790.3225806452,
						0,
						441
					]
				],
				"typeOfSection": 0,
				"gfSection": false,
				"altAnim": false,
				"mustHitSection": false,
				"changeBPM": false,
				"bpm": 160
			},
			{
				"sectionBeats": 4,
				"sectionNotes": [
					[
						83290.3225806452,
						5,
						190
					],
					[
						83540.3225806452,
						6,
						0
					],
					[
						83790.3225806452,
						4,
						189
					],
					[
						83696.5725806452,
						5,
						0
					],
					[
						84040.3225806452,
						7,
						189
					]
				],
				"typeOfSection": 0,
				"gfSection": false,
				"altAnim": false,
				"mustHitSection": false,
				"changeBPM": false,
				"bpm": 160
			},
			{
				"sectionBeats": 4,
				"sectionNotes": [
					[
						84290.3225806452,
						5,
						0
					],
					[
						84352.8225806452,
						4,
						0
					],
					[
						84415.3225806452,
						7,
						0
					],
					[
						84540.3225806452,
						6,
						0
					],
					[
						84790.3225806452,
						5,
						189
					],
					[
						84696.5725806452,
						6,
						0
					],
					[
						85040.3225806452,
						6,
						189
					]
				],
				"typeOfSection": 0,
				"gfSection": false,
				"altAnim": false,
				"mustHitSection": false,
				"changeBPM": false,
				"bpm": 160
			},
			{
				"sectionBeats": 4,
				"sectionNotes": [
					[
						85290.3225806452,
						7,
						189
					],
					[
						85540.3225806452,
						5,
						0
					],
					[
						85696.5725806452,
						5,
						0
					],
					[
						85790.3225806452,
						4,
						189
					],
					[
						86040.3225806452,
						6,
						190
					]
				],
				"typeOfSection": 0,
				"gfSection": false,
				"altAnim": false,
				"mustHitSection": false,
				"changeBPM": false,
				"bpm": 160
			},
			{
				"sectionBeats": 4,
				"sectionNotes": [
					[
						86290.3225806452,
						5,
						0
					],
					[
						86415.3225806452,
						7,
						0
					],
					[
						86352.8225806452,
						4,
						0
					],
					[
						86540.3225806452,
						6,
						0
					],
					[
						86696.5725806452,
						5,
						0
					],
					[
						86790.3225806452,
						6,
						0
					],
					[
						86946.5725806452,
						5,
						0
					],
					[
						87040.3225806452,
						4,
						0
					],
					[
						87196.5725806452,
						7,
						0
					]
				],
				"typeOfSection": 0,
				"gfSection": false,
				"altAnim": false,
				"mustHitSection": false,
				"changeBPM": false,
				"bpm": 160
			},
			{
				"sectionBeats": 4,
				"sectionNotes": [
					[
						87290.3225806452,
						6,
						693
					],
					[
						88040.3225806452,
						4,
						0
					],
					[
						88196.5725806452,
						7,
						0
					]
				],
				"typeOfSection": 0,
				"gfSection": false,
				"altAnim": false,
				"mustHitSection": false,
				"changeBPM": false,
				"bpm": 160
			},
			{
				"sectionBeats": 4,
				"sectionNotes": [
					[
						88290.3225806452,
						6,
						189
					],
					[
						88540.3225806452,
						5,
						189
					],
					[
						88790.3225806452,
						6,
						126
					],
					[
						89040.3225806452,
						6,
						189
					]
				],
				"typeOfSection": 0,
				"gfSection": false,
				"altAnim": false,
				"mustHitSection": false,
				"changeBPM": false,
				"bpm": 160
			},
			{
				"sectionBeats": 4,
				"sectionNotes": [
					[
						89290.3225806452,
						7,
						693
					],
					[
						89290.3225806452,
						4,
						630
					],
					[
						90040.3225806452,
						6,
						0
					],
					[
						90196.5725806452,
						5,
						0
					]
				],
				"typeOfSection": 0,
				"gfSection": false,
				"altAnim": false,
				"mustHitSection": false,
				"changeBPM": false,
				"bpm": 160
			},
			{
				"sectionBeats": 4,
				"sectionNotes": [
					[
						90290.3225806452,
						6,
						441
					],
					[
						90790.3225806452,
						7,
						441
					]
				],
				"typeOfSection": 0,
				"gfSection": false,
				"altAnim": false,
				"mustHitSection": false,
				"changeBPM": false,
				"bpm": 160
			},
			{
				"sectionBeats": 4,
				"sectionNotes": [
					[
						91290.3225806452,
						4,
						1890
					],
					[
						91290.3225806452,
						5,
						1953
					],
					[
						91290.3225806452,
						0,
						1393
					]
				],
				"typeOfSection": 0,
				"gfSection": false,
				"altAnim": false,
				"mustHitSection": false,
				"changeBPM": false,
				"bpm": 160
			},
			{
				"sectionBeats": 4,
				"sectionNotes": [
					[
						93196.5725806452,
						2,
						0
					],
					[
						92790.3225806452,
						2,
						0
					],
					[
						93040.3225806452,
						1,
						0
					]
				],
				"typeOfSection": 0,
				"gfSection": false,
				"altAnim": false,
				"mustHitSection": false,
				"changeBPM": false,
				"bpm": 160
			},
			{
				"sectionBeats": 4,
				"sectionNotes": [
					[
						93290.3225806452,
						3,
						693
					],
					[
						94040.3225806452,
						2,
						693
					]
				],
				"typeOfSection": 0,
				"gfSection": false,
				"altAnim": false,
				"mustHitSection": false,
				"changeBPM": false,
				"bpm": 160
			},
			{
				"sectionBeats": 4,
				"sectionNotes": [
					[
						94790.3225806452,
						0,
						0
					],
					[
						94946.5725806452,
						1,
						0
					],
					[
						95040.3225806452,
						3,
						0
					],
					[
						95196.5725806452,
						1,
						0
					]
				],
				"typeOfSection": 0,
				"gfSection": false,
				"altAnim": false,
				"mustHitSection": false,
				"changeBPM": false,
				"bpm": 160
			},
			{
				"sectionBeats": 4,
				"sectionNotes": [
					[
						95290.3225806452,
						0,
						693
					],
					[
						96040.3225806452,
						3,
						441
					]
				],
				"typeOfSection": 0,
				"gfSection": false,
				"altAnim": false,
				"mustHitSection": false,
				"changeBPM": false,
				"bpm": 160
			},
			{
				"sectionBeats": 4,
				"sectionNotes": [
					[
						96540.3225806452,
						2,
						315
					],
					[
						96915.3225806452,
						3,
						315
					]
				],
				"typeOfSection": 0,
				"gfSection": false,
				"altAnim": false,
				"mustHitSection": false,
				"changeBPM": false,
				"bpm": 160
			},
			{
				"sectionBeats": 4,
				"sectionNotes": [
					[
						97290.3225806452,
						0,
						945
					]
				],
				"typeOfSection": 0,
				"gfSection": false,
				"altAnim": false,
				"mustHitSection": false,
				"changeBPM": false,
				"bpm": 160
			},
			{
				"sectionBeats": 4,
				"sectionNotes": [
					[
						98290.3225806452,
						1,
						441
					],
					[
						98290.3225806452,
						2,
						441
					],
					[
						98790.3225806452,
						3,
						189
					],
					[
						99040.3225806452,
						1,
						0
					],
					[
						99196.5725806452,
						0,
						0
					]
				],
				"typeOfSection": 0,
				"gfSection": false,
				"altAnim": false,
				"mustHitSection": false,
				"changeBPM": false,
				"bpm": 160
			},
			{
				"sectionBeats": 4,
				"sectionNotes": [
					[
						99290.3225806452,
						4,
						1393
					],
					[
						99290.3225806452,
						1,
						1701
					]
				],
				"typeOfSection": 0,
				"gfSection": false,
				"altAnim": false,
				"mustHitSection": false,
				"changeBPM": false,
				"bpm": 160
			},
			{
				"sectionBeats": 4,
				"sectionNotes": [
					[
						101196.572580645,
						5,
						0
					],
					[
						100790.322580645,
						5,
						0
					],
					[
						101040.322580645,
						6,
						0
					]
				],
				"typeOfSection": 0,
				"gfSection": false,
				"altAnim": false,
				"mustHitSection": false,
				"changeBPM": false,
				"bpm": 160
			},
			{
				"sectionBeats": 4,
				"sectionNotes": [
					[
						101290.322580645,
						4,
						693
					],
					[
						102040.322580645,
						5,
						693
					]
				],
				"typeOfSection": 0,
				"gfSection": false,
				"altAnim": false,
				"mustHitSection": false,
				"changeBPM": false,
				"bpm": 160
			},
			{
				"sectionBeats": 4,
				"sectionNotes": [
					[
						102790.322580645,
						7,
						0
					],
					[
						102946.572580645,
						6,
						0
					],
					[
						103040.322580645,
						5,
						0
					],
					[
						103196.572580645,
						4,
						0
					]
				],
				"typeOfSection": 0,
				"gfSection": false,
				"altAnim": false,
				"mustHitSection": false,
				"changeBPM": false,
				"bpm": 160
			},
			{
				"sectionBeats": 4,
				"sectionNotes": [
					[
						103290.322580645,
						7,
						693
					],
					[
						104040.322580645,
						6,
						694
					]
				],
				"typeOfSection": 0,
				"gfSection": false,
				"altAnim": false,
				"mustHitSection": false,
				"changeBPM": false,
				"bpm": 160
			},
			{
				"sectionBeats": 4,
				"sectionNotes": [
					[
						104790.322580645,
						5,
						441
					]
				],
				"typeOfSection": 0,
				"gfSection": false,
				"altAnim": false,
				"mustHitSection": false,
				"changeBPM": false,
				"bpm": 160
			},
			{
				"sectionBeats": 4,
				"sectionNotes": [
					[
						105290.322580645,
						4,
						945
					]
				],
				"typeOfSection": 0,
				"gfSection": false,
				"altAnim": false,
				"mustHitSection": false,
				"changeBPM": false,
				"bpm": 160
			},
			{
				"sectionBeats": 4,
				"sectionNotes": [
					[
						106290.322580645,
						5,
						379
					],
					[
						106290.322580645,
						7,
						441
					],
					[
						106790.322580645,
						6,
						189
					],
					[
						107040.322580645,
						4,
						0
					],
					[
						107196.572580645,
						7,
						0
					]
				],
				"typeOfSection": 0,
				"gfSection": false,
				"altAnim": false,
				"mustHitSection": false,
				"changeBPM": false,
				"bpm": 160
			},
			{
				"sectionBeats": 4,
				"sectionNotes": [
					[
						107290.322580645,
						1,
						0
					],
					[
						107540.322580645,
						1,
						0
					],
					[
						107446.572580645,
						2,
						0
					],
					[
						107696.572580645,
						3,
						0
					],
					[
						107790.322580645,
						0,
						189
					],
					[
						108040.322580645,
						1,
						189
					],
					[
						107290.322580645,
						6,
						945
					]
				],
				"typeOfSection": 0,
				"gfSection": false,
				"altAnim": false,
				"mustHitSection": false,
				"changeBPM": false,
				"bpm": 160
			},
			{
				"sectionBeats": 4,
				"sectionNotes": [
					[
						108290.322580645,
						3,
						0
					],
					[
						108540.322580645,
						3,
						0
					],
					[
						108446.572580645,
						2,
						0
					],
					[
						108790.322580645,
						0,
						189
					],
					[
						108696.572580645,
						1,
						0
					],
					[
						109040.322580645,
						2,
						189
					]
				],
				"typeOfSection": 0,
				"gfSection": false,
				"altAnim": false,
				"mustHitSection": false,
				"changeBPM": false,
				"bpm": 160
			},
			{
				"sectionBeats": 4,
				"sectionNotes": [
					[
						109415.322580645,
						2,
						315
					],
					[
						109915.322580645,
						2,
						315
					],
					[
						109290.322580645,
						1,
						0
					],
					[
						109790.322580645,
						3,
						0
					]
				],
				"typeOfSection": 0,
				"gfSection": false,
				"altAnim": false,
				"mustHitSection": false,
				"changeBPM": false,
				"bpm": 160
			},
			{
				"sectionBeats": 4,
				"sectionNotes": [
					[
						110290.322580645,
						0,
						0
					],
					[
						110540.322580645,
						0,
						0
					],
					[
						110446.572580645,
						1,
						0
					],
					[
						110790.322580645,
						2,
						0
					],
					[
						110696.572580645,
						3,
						0
					],
					[
						111196.572580645,
						1,
						0
					],
					[
						111040.322580645,
						2,
						0
					],
					[
						110946.572580645,
						1,
						0
					]
				],
				"typeOfSection": 0,
				"gfSection": false,
				"altAnim": false,
				"mustHitSection": false,
				"changeBPM": false,
				"bpm": 160
			},
			{
				"sectionBeats": 4,
				"sectionNotes": [
					[
						111290.322580645,
						0,
						693
					],
					[
						112040.322580645,
						3,
						693
					]
				],
				"typeOfSection": 0,
				"gfSection": false,
				"altAnim": false,
				"mustHitSection": false,
				"changeBPM": false,
				"bpm": 160
			},
			{
				"sectionBeats": 4,
				"sectionNotes": [
					[
						112790.322580645,
						2,
						441
					]
				],
				"typeOfSection": 0,
				"gfSection": false,
				"altAnim": false,
				"mustHitSection": false,
				"changeBPM": false,
				"bpm": 160
			},
			{
				"sectionBeats": 4,
				"sectionNotes": [
					[
						113290.322580645,
						0,
						694
					],
					[
						114040.322580645,
						3,
						693
					]
				],
				"typeOfSection": 0,
				"gfSection": false,
				"altAnim": false,
				"mustHitSection": false,
				"changeBPM": false,
				"bpm": 160
			},
			{
				"sectionBeats": 4,
				"sectionNotes": [
					[
						114790.322580645,
						2,
						441
					]
				],
				"typeOfSection": 0,
				"gfSection": false,
				"altAnim": false,
				"mustHitSection": false,
				"changeBPM": false,
				"bpm": 160
			},
			{
				"sectionBeats": 4,
				"sectionNotes": [
					[
						115290.322580645,
						1,
						189
					],
					[
						115665.322580645,
						1,
						0
					],
					[
						116040.322580645,
						0,
						189
					],
					[
						115790.322580645,
						4,
						189
					],
					[
						115290.322580645,
						6,
						0
					],
					[
						115446.572580645,
						7,
						0
					],
					[
						115540.322580645,
						6,
						0
					],
					[
						115696.572580645,
						5,
						0
					],
					[
						116040.322580645,
						7,
						189
					]
				],
				"typeOfSection": 0,
				"gfSection": false,
				"altAnim": false,
				"mustHitSection": false,
				"changeBPM": false,
				"bpm": 160
			},
			{
				"sectionBeats": 4,
				"sectionNotes": [
					[
						116415.322580645,
						3,
						63
					],
					[
						116790.322580645,
						1,
						0
					],
					[
						117040.322580645,
						1,
						0
					],
					[
						116290.322580645,
						6,
						189
					],
					[
						116540.322580645,
						5,
						0
					],
					[
						116696.572580645,
						6,
						0
					],
					[
						116790.322580645,
						7,
						189
					],
					[
						117040.322580645,
						4,
						189
					]
				],
				"typeOfSection": 0,
				"gfSection": false,
				"altAnim": false,
				"mustHitSection": false,
				"changeBPM": false,
				"bpm": 160
			},
			{
				"sectionBeats": 4,
				"sectionNotes": [
					[
						117290.322580645,
						2,
						189
					],
					[
						118040.322580645,
						3,
						189
					],
					[
						117665.322580645,
						2,
						0
					],
					[
						117290.322580645,
						5,
						0
					],
					[
						117915.322580645,
						4,
						315
					],
					[
						117415.322580645,
						6,
						315
					],
					[
						117790.322580645,
						5,
						0
					]
				],
				"typeOfSection": 0,
				"gfSection": false,
				"altAnim": false,
				"mustHitSection": false,
				"changeBPM": false,
				"bpm": 160
			},
			{
				"sectionBeats": 4,
				"sectionNotes": [
					[
						118415.322580645,
						0,
						0
					],
					[
						118790.322580645,
						1,
						0
					],
					[
						119040.322580645,
						1,
						189
					],
					[
						119040.322580645,
						6,
						0
					],
					[
						118946.572580645,
						5,
						0
					],
					[
						118290.322580645,
						7,
						0
					],
					[
						118446.572580645,
						6,
						0
					],
					[
						118540.322580645,
						5,
						0
					],
					[
						118696.572580645,
						4,
						0
					],
					[
						118790.322580645,
						7,
						0
					],
					[
						119196.572580645,
						4,
						0
					]
				],
				"typeOfSection": 0,
				"gfSection": false,
				"altAnim": false,
				"mustHitSection": false,
				"changeBPM": false,
				"bpm": 160
			},
			{
				"sectionBeats": 4,
				"sectionNotes": [
					[
						119290.322580645,
						2,
						189
					],
					[
						120040.322580645,
						3,
						189
					],
					[
						119665.322580645,
						1,
						0
					],
					[
						119290.322580645,
						7,
						693
					],
					[
						120040.322580645,
						6,
						693
					]
				],
				"typeOfSection": 0,
				"gfSection": false,
				"altAnim": false,
				"mustHitSection": false,
				"changeBPM": false,
				"bpm": 160
			},
			{
				"sectionBeats": 4,
				"sectionNotes": [
					[
						120415.322580645,
						0,
						63
					],
					[
						120790.322580645,
						1,
						0
					],
					[
						121040.322580645,
						1,
						126
					],
					[
						120790.322580645,
						4,
						441
					]
				],
				"typeOfSection": 0,
				"gfSection": false,
				"altAnim": false,
				"mustHitSection": false,
				"changeBPM": false,
				"bpm": 160
			},
			{
				"sectionBeats": 4,
				"sectionNotes": [
					[
						121290.322580645,
						2,
						189
					],
					[
						122040.322580645,
						0,
						189
					],
					[
						121665.322580645,
						3,
						0
					],
					[
						122040.322580645,
						7,
						693
					],
					[
						121290.322580645,
						5,
						693
					]
				],
				"typeOfSection": 0,
				"gfSection": false,
				"altAnim": false,
				"mustHitSection": false,
				"changeBPM": false,
				"bpm": 160
			},
			{
				"sectionBeats": 4,
				"sectionNotes": [
					[
						122790.322580645,
						1,
						0
					],
					[
						123040.322580645,
						1,
						189
					],
					[
						122415.322580645,
						2,
						0
					],
					[
						122790.322580645,
						6,
						441
					]
				],
				"typeOfSection": 0,
				"gfSection": false,
				"altAnim": false,
				"mustHitSection": false,
				"changeBPM": false,
				"bpm": 160
			},
			{
				"sectionBeats": 4,
				"sectionNotes": [
					[
						123290.322580645,
						4,
						1953
					]
				],
				"typeOfSection": 0,
				"gfSection": false,
				"altAnim": false,
				"mustHitSection": false,
				"changeBPM": false,
				"bpm": 160
			},
			{
				"sectionBeats": 4,
				"sectionNotes": [
					[
						124602.822580645,
						5,
						630
					]
				],
				"typeOfSection": 0,
				"gfSection": false,
				"altAnim": false,
				"mustHitSection": false,
				"changeBPM": false,
				"bpm": 160
			},
			{
				"sectionBeats": 4,
				"sectionNotes": [],
				"typeOfSection": 0,
				"gfSection": false,
				"altAnim": false,
				"mustHitSection": false,
				"changeBPM": false,
				"bpm": 160
			},
			{
				"sectionBeats": 4,
				"sectionNotes": [
					[
						126665.322580645,
						1,
						134
					],
					[
						126524.697580645,
						0,
						0
					],
					[
						127040.322580645,
						1,
						134
					],
					[
						126899.697580645,
						2,
						0
					],
					[
						127415.322580645,
						3,
						134
					],
					[
						127274.697580645,
						2,
						0
					],
					[
						127649.697580645,
						1,
						0
					],
					[
						126290.322580645,
						1,
						137
					]
				],
				"typeOfSection": 0,
				"gfSection": false,
				"altAnim": false,
				"mustHitSection": false,
				"changeBPM": true,
				"bpm": 160
			},
			{
				"sectionBeats": 4,
				"sectionNotes": [
					[
						127790.322580645,
						0,
						0
					],
					[
						128540.322580645,
						3,
						282
					],
					[
						128024.697580645,
						1,
						0
					],
					[
						128165.322580645,
						2,
						0
					],
					[
						128399.697580645,
						0,
						0
					],
					[
						128915.322580645,
						2,
						282
					]
				],
				"typeOfSection": 0,
				"gfSection": false,
				"altAnim": false,
				"mustHitSection": false,
				"changeBPM": false,
				"bpm": 160
			},
			{
				"sectionBeats": 4,
				"sectionNotes": [
					[
						129665.322580645,
						0,
						0
					],
					[
						130040.322580645,
						2,
						0
					],
					[
						129899.697580645,
						3,
						0
					],
					[
						130415.322580645,
						2,
						0
					],
					[
						130274.697580645,
						1,
						0
					],
					[
						130649.697580645,
						1,
						0
					],
					[
						129524.697580645,
						1,
						0
					]
				],
				"typeOfSection": 0,
				"gfSection": false,
				"altAnim": false,
				"mustHitSection": false,
				"changeBPM": false,
				"bpm": 160
			},
			{
				"sectionBeats": 4,
				"sectionNotes": [
					[
						130790.322580645,
						0,
						94
					],
					[
						131165.322580645,
						2,
						0
					],
					[
						131024.697580645,
						3,
						0
					],
					[
						131540.322580645,
						2,
						188
					],
					[
						131399.697580645,
						1,
						0
					],
					[
						131915.322580645,
						3,
						282
					]
				],
				"typeOfSection": 0,
				"gfSection": false,
				"altAnim": false,
				"mustHitSection": false,
				"changeBPM": false,
				"bpm": 160
			},
			{
				"sectionBeats": 4,
				"sectionNotes": [
					[
						132665.322580645,
						6,
						134
					],
					[
						133040.322580645,
						6,
						134
					],
					[
						132290.322580645,
						6,
						137
					],
					[
						132290.322580645,
						0,
						1410
					],
					[
						132290.322580645,
						1,
						1316
					],
					[
						133274.697580645,
						4,
						0
					],
					[
						132524.697580645,
						5,
						0
					],
					[
						132899.697580645,
						7,
						0
					],
					[
						133415.322580645,
						5,
						134
					],
					[
						133649.697580645,
						7,
						0
					]
				],
				"typeOfSection": 0,
				"gfSection": false,
				"altAnim": false,
				"mustHitSection": false,
				"changeBPM": false,
				"bpm": 160
			},
			{
				"sectionBeats": 4,
				"sectionNotes": [
					[
						133790.322580645,
						6,
						0
					],
					[
						134165.322580645,
						5,
						0
					],
					[
						134024.697580645,
						4,
						0
					],
					[
						134399.697580645,
						7,
						0
					],
					[
						134540.322580645,
						6,
						188
					],
					[
						134915.322580645,
						4,
						282
					]
				],
				"typeOfSection": 0,
				"gfSection": false,
				"altAnim": false,
				"mustHitSection": false,
				"changeBPM": false,
				"bpm": 160
			},
			{
				"sectionBeats": 4,
				"sectionNotes": [
					[
						135665.322580645,
						4,
						0
					],
					[
						136040.322580645,
						6,
						0
					],
					[
						135899.697580645,
						7,
						0
					],
					[
						136415.322580645,
						6,
						0
					],
					[
						136274.697580645,
						5,
						0
					],
					[
						135524.697580645,
						5,
						0
					],
					[
						136649.697580645,
						5,
						0
					]
				],
				"typeOfSection": 0,
				"gfSection": false,
				"altAnim": false,
				"mustHitSection": false,
				"changeBPM": false,
				"bpm": 160
			},
			{
				"sectionBeats": 4,
				"sectionNotes": [
					[
						137915.322580645,
						7,
						282
					],
					[
						136790.322580645,
						4,
						94
					],
					[
						137399.697580645,
						4,
						0
					],
					[
						137540.322580645,
						5,
						94
					],
					[
						137024.697580645,
						7,
						0
					],
					[
						137165.322580645,
						6,
						0
					]
				],
				"typeOfSection": 0,
				"gfSection": false,
				"altAnim": false,
				"mustHitSection": false,
				"changeBPM": false,
				"bpm": 160
			},
			{
				"sectionBeats": 4,
				"sectionNotes": [
					[
						138290.322580645,
						6,
						1786
					],
					[
						138665.322580645,
						1,
						134
					],
					[
						138524.697580645,
						0,
						0
					],
					[
						139040.322580645,
						1,
						134
					],
					[
						138899.697580645,
						2,
						0
					],
					[
						139415.322580645,
						3,
						134
					],
					[
						139274.697580645,
						2,
						0
					],
					[
						138290.322580645,
						1,
						137
					],
					[
						139649.697580645,
						0,
						0
					]
				],
				"typeOfSection": 0,
				"gfSection": false,
				"altAnim": false,
				"mustHitSection": false,
				"changeBPM": false,
				"bpm": 160
			},
			{
				"sectionBeats": 4,
				"sectionNotes": [
					[
						139790.322580645,
						2,
						0
					],
					[
						140540.322580645,
						3,
						472
					],
					[
						139915.322580645,
						1,
						0
					],
					[
						140040.322580645,
						3,
						0
					],
					[
						140165.322580645,
						2,
						0
					],
					[
						140290.322580645,
						0,
						0
					],
					[
						140415.322580645,
						1,
						0
					],
					[
						141149.697580645,
						2,
						0
					]
				],
				"typeOfSection": 0,
				"gfSection": false,
				"altAnim": false,
				"mustHitSection": false,
				"changeBPM": false,
				"bpm": 160
			},
			{
				"sectionBeats": 4,
				"sectionNotes": [
					[
						141290.322580645,
						1,
						0
					],
					[
						141665.322580645,
						0,
						0
					],
					[
						141790.322580645,
						2,
						0
					],
					[
						141415.322580645,
						3,
						0
					],
					[
						141540.322580645,
						2,
						0
					],
					[
						141915.322580645,
						1,
						0
					],
					[
						142040.322580645,
						3,
						0
					],
					[
						142290.322580645,
						0,
						0
					],
					[
						142696.572580645,
						1,
						149
					],
					[
						142696.572580645,
						3,
						0
					],
					[
						142415.322580645,
						2,
						188
					],
					[
						142165.322580645,
						1,
						0
					]
				],
				"typeOfSection": 0,
				"gfSection": false,
				"altAnim": false,
				"mustHitSection": false,
				"changeBPM": false,
				"bpm": 160
			},
			{
				"sectionBeats": 4,
				"sectionNotes": [
					[
						143165.322580645,
						0,
						0
					],
					[
						143290.322580645,
						2,
						0
					],
					[
						143415.322580645,
						1,
						0
					],
					[
						143540.322580645,
						3,
						0
					],
					[
						143665.322580645,
						2,
						0
					],
					[
						143790.322580645,
						0,
						0
					],
					[
						143915.322580645,
						2,
						150
					],
					[
						142915.322580645,
						2,
						0
					],
					[
						143040.322580645,
						3,
						0
					],
					[
						144149.697580645,
						1,
						0
					]
				],
				"typeOfSection": 0,
				"gfSection": false,
				"altAnim": false,
				"mustHitSection": false,
				"changeBPM": false,
				"bpm": 160
			},
			{
				"sectionBeats": 4,
				"sectionNotes": [
					[
						144665.322580645,
						6,
						134
					],
					[
						144524.697580645,
						7,
						0
					],
					[
						145040.322580645,
						6,
						134
					],
					[
						144899.697580645,
						5,
						0
					],
					[
						144290.322580645,
						6,
						137
					],
					[
						145649.697580645,
						7,
						0
					],
					[
						144290.322580645,
						3,
						941
					],
					[
						145274.697580645,
						4,
						0
					],
					[
						145415.322580645,
						5,
						149
					]
				],
				"typeOfSection": 0,
				"gfSection": false,
				"altAnim": false,
				"mustHitSection": false,
				"changeBPM": false,
				"bpm": 160
			},
			{
				"sectionBeats": 4,
				"sectionNotes": [
					[
						145790.322580645,
						6,
						0
					],
					[
						147149.697580645,
						6,
						0
					],
					[
						145915.322580645,
						4,
						0
					],
					[
						146040.322580645,
						5,
						0
					],
					[
						146165.322580645,
						7,
						0
					],
					[
						146290.322580645,
						6,
						0
					],
					[
						146415.322580645,
						4,
						0
					],
					[
						146540.322580645,
						5,
						470
					]
				],
				"typeOfSection": 0,
				"gfSection": false,
				"altAnim": false,
				"mustHitSection": false,
				"changeBPM": false,
				"bpm": 160
			},
			{
				"sectionBeats": 4,
				"sectionNotes": [
					[
						147290.322580645,
						5,
						0
					],
					[
						147790.322580645,
						6,
						0
					],
					[
						148040.322580645,
						7,
						0
					],
					[
						148290.322580645,
						4,
						0
					],
					[
						148415.322580645,
						6,
						149
					],
					[
						147415.322580645,
						4,
						0
					],
					[
						147540.322580645,
						7,
						0
					],
					[
						147665.322580645,
						5,
						0
					],
					[
						147915.322580645,
						4,
						0
					],
					[
						148165.322580645,
						5,
						0
					],
					[
						148649.697580645,
						7,
						0
					]
				],
				"typeOfSection": 0,
				"gfSection": false,
				"altAnim": false,
				"mustHitSection": false,
				"changeBPM": false,
				"bpm": 160
			},
			{
				"sectionBeats": 4,
				"sectionNotes": [
					[
						148915.322580645,
						6,
						0
					],
					[
						148790.322580645,
						5,
						0
					],
					[
						149290.322580645,
						7,
						0
					],
					[
						149415.322580645,
						6,
						0
					],
					[
						149540.322580645,
						4,
						0
					],
					[
						149665.322580645,
						5,
						0
					],
					[
						149790.322580645,
						7,
						0
					],
					[
						149040.322580645,
						5,
						0
					],
					[
						149165.322580645,
						4,
						0
					],
					[
						149915.322580645,
						6,
						94
					],
					[
						150165.322580645,
						5,
						0
					]
				],
				"typeOfSection": 0,
				"gfSection": false,
				"altAnim": false,
				"mustHitSection": false,
				"changeBPM": false,
				"bpm": 160
			},
			{
				"sectionBeats": 4,
				"sectionNotes": [
					[
						150290.322580645,
						6,
						0
					],
					[
						150415.322580645,
						5,
						0
					],
					[
						150540.322580645,
						4,
						0
					],
					[
						150665.322580645,
						7,
						1504
					],
					[
						150290.322580645,
						2,
						472
					],
					[
						150915.322580645,
						1,
						0
					],
					[
						151415.322580645,
						2,
						94
					],
					[
						151649.697580645,
						1,
						0
					],
					[
						151040.322580645,
						2,
						0
					],
					[
						151165.322580645,
						0,
						0
					],
					[
						151290.322580645,
						3,
						0
					]
				],
				"typeOfSection": 0,
				"gfSection": false,
				"altAnim": false,
				"mustHitSection": false,
				"changeBPM": false,
				"bpm": 160
			},
			{
				"sectionBeats": 4,
				"sectionNotes": [
					[
						152282.510080645,
						1,
						0
					],
					[
						152915.322580645,
						0,
						376
					],
					[
						152024.697580645,
						2,
						0
					],
					[
						152165.322580645,
						2,
						0
					],
					[
						152399.697580645,
						3,
						0
					],
					[
						152540.322580645,
						2,
						282
					],
					[
						151790.322580645,
						0,
						94
					]
				],
				"typeOfSection": 0,
				"gfSection": false,
				"altAnim": false,
				"mustHitSection": false,
				"changeBPM": false,
				"bpm": 160
			},
			{
				"sectionBeats": 4,
				"sectionNotes": [
					[
						153665.322580645,
						2,
						0
					],
					[
						153524.697580645,
						1,
						0
					],
					[
						154649.697580645,
						0,
						0
					],
					[
						153884.072580645,
						1,
						0
					],
					[
						154009.072580645,
						0,
						0
					],
					[
						154134.072580645,
						3,
						0
					],
					[
						154259.072580645,
						1,
						0
					],
					[
						154384.072580645,
						2,
						134
					]
				],
				"typeOfSection": 0,
				"gfSection": false,
				"altAnim": false,
				"mustHitSection": false,
				"changeBPM": false,
				"bpm": 160
			},
			{
				"sectionBeats": 4,
				"sectionNotes": [
					[
						154790.322580645,
						1,
						565
					],
					[
						154790.322580645,
						3,
						470
					],
					[
						155540.322580645,
						2,
						282
					],
					[
						155915.322580645,
						0,
						282
					]
				],
				"typeOfSection": 0,
				"gfSection": false,
				"altAnim": false,
				"mustHitSection": false,
				"changeBPM": false,
				"bpm": 160
			},
			{
				"sectionBeats": 4,
				"sectionNotes": [
					[
						157165.322580645,
						4,
						0
					],
					[
						156290.322580645,
						4,
						470
					],
					[
						156915.322580645,
						6,
						0
					],
					[
						157040.322580645,
						7,
						0
					],
					[
						157290.322580645,
						6,
						0
					],
					[
						157415.322580645,
						5,
						95
					],
					[
						157649.697580645,
						4,
						0
					]
				],
				"typeOfSection": 0,
				"gfSection": false,
				"altAnim": false,
				"mustHitSection": false,
				"changeBPM": false,
				"bpm": 160
			},
			{
				"sectionBeats": 4,
				"sectionNotes": [
					[
						158282.510080645,
						5,
						0
					],
					[
						158915.322580645,
						4,
						376
					],
					[
						158024.697580645,
						6,
						0
					],
					[
						158165.322580645,
						6,
						0
					],
					[
						158399.697580645,
						7,
						0
					],
					[
						158540.322580645,
						6,
						282
					],
					[
						157790.322580645,
						7,
						94
					]
				],
				"typeOfSection": 0,
				"gfSection": false,
				"altAnim": false,
				"mustHitSection": false,
				"changeBPM": false,
				"bpm": 160
			},
			{
				"sectionBeats": 4,
				"sectionNotes": [
					[
						159665.322580645,
						5,
						94
					],
					[
						159524.697580645,
						6,
						0
					],
					[
						159884.072580645,
						6,
						0
					],
					[
						160009.072580645,
						7,
						0
					],
					[
						160134.072580645,
						4,
						0
					],
					[
						160259.072580645,
						6,
						0
					],
					[
						160384.072580645,
						5,
						134
					],
					[
						160649.697580645,
						4,
						0
					]
				],
				"typeOfSection": 0,
				"gfSection": false,
				"altAnim": false,
				"mustHitSection": false,
				"changeBPM": false,
				"bpm": 160
			},
			{
				"sectionBeats": 4,
				"sectionNotes": [
					[
						160790.322580645,
						6,
						470
					],
					[
						160790.322580645,
						7,
						564
					],
					[
						161540.322580645,
						4,
						282
					],
					[
						161915.322580645,
						5,
						282
					],
					[
						161915.322580645,
						6,
						188
					]
				],
				"typeOfSection": 0,
				"gfSection": false,
				"altAnim": false,
				"mustHitSection": false,
				"changeBPM": false,
				"bpm": 160
			},
			{
				"sectionBeats": 4,
				"sectionNotes": [],
				"typeOfSection": 0,
				"gfSection": false,
				"altAnim": false,
				"mustHitSection": false,
				"changeBPM": false,
				"bpm": 160
			},
			{
				"sectionBeats": 4,
				"sectionNotes": [],
				"typeOfSection": 0,
				"gfSection": false,
				"altAnim": false,
				"mustHitSection": false,
				"changeBPM": true,
				"bpm": 120
			},
			{
				"sectionBeats": 4,
				"sectionNotes": [],
				"typeOfSection": 0,
				"gfSection": false,
				"altAnim": false,
				"mustHitSection": false,
				"changeBPM": false,
				"bpm": 160
			},
			{
				"sectionBeats": 4,
				"sectionNotes": [],
				"typeOfSection": 0,
				"gfSection": false,
				"altAnim": false,
				"mustHitSection": false,
				"changeBPM": false,
				"bpm": 160
			},
			{
				"sectionBeats": 4,
				"sectionNotes": [],
				"typeOfSection": 0,
				"gfSection": false,
				"altAnim": false,
				"mustHitSection": false,
				"changeBPM": false,
				"bpm": 160
			},
			{
				"sectionBeats": 4,
				"sectionNotes": [
					[
						171790.322580645,
						4,
						875
					],
					[
						172790.322580645,
						6,
						625
					],
					[
						172790.322580645,
						7,
						875
					]
				],
				"typeOfSection": 0,
				"gfSection": false,
				"altAnim": false,
				"mustHitSection": false,
				"changeBPM": false,
				"bpm": 160
			},
			{
				"sectionBeats": 4,
				"sectionNotes": [
					[
						173790.322580645,
						5,
						875
					],
					[
						174790.322580645,
						6,
						875
					]
				],
				"typeOfSection": 0,
				"gfSection": false,
				"altAnim": false,
				"mustHitSection": false,
				"changeBPM": false,
				"bpm": 160
			},
			{
				"sectionBeats": 4,
				"sectionNotes": [
					[
						175790.322580645,
						4,
						1875
					]
				],
				"typeOfSection": 0,
				"gfSection": false,
				"altAnim": false,
				"mustHitSection": false,
				"changeBPM": false,
				"bpm": 160
			},
			{
				"sectionBeats": 4,
				"sectionNotes": [
					[
						177790.322580645,
						7,
						1875
					]
				],
				"typeOfSection": 0,
				"gfSection": false,
				"altAnim": false,
				"mustHitSection": false,
				"changeBPM": false,
				"bpm": 160
			},
			{
				"sectionBeats": 4,
				"sectionNotes": [
					[
						180790.322580645,
						3,
						750
					],
					[
						179790.322580645,
						2,
						875
					],
					[
						180790.322580645,
						1,
						875
					]
				],
				"typeOfSection": 0,
				"gfSection": false,
				"altAnim": false,
				"mustHitSection": false,
				"changeBPM": false,
				"bpm": 160
			},
			{
				"sectionBeats": 4,
				"sectionNotes": [
					[
						182790.322580645,
						2,
						875
					],
					[
						181790.322580645,
						0,
						875
					]
				],
				"typeOfSection": 0,
				"gfSection": false,
				"altAnim": false,
				"mustHitSection": false,
				"changeBPM": false,
				"bpm": 160
			},
			{
				"sectionBeats": 4,
				"sectionNotes": [
					[
						183790.322580645,
						1,
						1625
					],
					[
						185540.322580645,
						2,
						0
					],
					[
						185706.989247312,
						3,
						0
					]
				],
				"typeOfSection": 0,
				"gfSection": false,
				"altAnim": false,
				"mustHitSection": false,
				"changeBPM": false,
				"bpm": 139.5
			},
			{
				"sectionBeats": 4,
				"sectionNotes": [
					[
						185790.322580645,
						2,
						875
					],
					[
						186790.322580645,
						0,
						375
					],
					[
						187290.322580645,
						2,
						375
					]
				],
				"typeOfSection": 0,
				"gfSection": false,
				"altAnim": false,
				"mustHitSection": false,
				"changeBPM": false,
				"bpm": 139.5
			},
			{
				"sectionBeats": 4,
				"sectionNotes": [],
				"typeOfSection": 0,
				"gfSection": false,
				"altAnim": false,
				"mustHitSection": false,
				"changeBPM": false,
				"bpm": 139.5
			},
			{
				"sectionBeats": 4,
				"sectionNotes": [],
				"typeOfSection": 0,
				"gfSection": false,
				"altAnim": false,
				"mustHitSection": false,
				"changeBPM": false,
				"bpm": 139.5
			},
			{
				"sectionBeats": 4,
				"sectionNotes": [],
				"typeOfSection": 0,
				"gfSection": false,
				"altAnim": false,
				"mustHitSection": false,
				"changeBPM": false,
				"bpm": 139.5
			},
			{
				"sectionBeats": 4,
				"sectionNotes": [],
				"typeOfSection": 0,
				"gfSection": false,
				"altAnim": false,
				"mustHitSection": false,
				"changeBPM": false,
				"bpm": 139.5
			},
			{
				"sectionBeats": 4,
				"sectionNotes": [],
				"typeOfSection": 0,
				"gfSection": false,
				"altAnim": false,
				"mustHitSection": false,
				"changeBPM": false,
				"bpm": 139.5
			},
			{
				"sectionBeats": 4,
				"sectionNotes": [
					[
						198165.322580645,
						3,
						875
					],
					[
						198165.322580645,
						2,
						875
					],
					[
						198165.322580645,
						0,
						875
					],
					[
						198165.322580645,
						1,
						875
					]
				],
				"typeOfSection": 0,
				"gfSection": false,
				"altAnim": false,
				"mustHitSection": false,
				"changeBPM": false,
				"bpm": 139.5
			},
			{
				"sectionBeats": 4,
				"sectionNotes": [],
				"typeOfSection": 0,
				"gfSection": false,
				"altAnim": false,
				"mustHitSection": false,
				"changeBPM": false,
				"bpm": 139.5
			},
			{
				"typeOfSection": 0,
				"sectionNotes": [],
				"sectionBeats": 4,
				"altAnim": false,
				"gfSection": false,
				"bpm": 139.5,
				"changeBPM": false,
				"mustHitSection": true
			},
			{
				"typeOfSection": 0,
				"sectionNotes": [],
				"sectionBeats": 4,
				"altAnim": false,
				"gfSection": false,
				"bpm": 139.5,
				"changeBPM": false,
				"mustHitSection": true
			},
			{
				"sectionBeats": 4,
				"sectionNotes": [],
				"typeOfSection": 0,
				"gfSection": false,
				"altAnim": false,
				"mustHitSection": true,
				"changeBPM": false,
				"bpm": 139.5
			},
			{
				"gfSection": false,
				"altAnim": false,
				"typeOfSection": 0,
				"sectionNotes": [],
				"bpm": 139.5,
				"sectionBeats": 4,
				"changeBPM": false,
				"mustHitSection": true
			},
			{
				"gfSection": false,
				"altAnim": false,
				"typeOfSection": 0,
				"sectionNotes": [],
				"bpm": 139.5,
				"sectionBeats": 4,
				"changeBPM": false,
				"mustHitSection": true
			}
		],
		"gfVersion": "no-gf",
		"events": [
			[
				0,
				[
					[
						"middlescroll",
						"",
						""
					]
				]
			],
			[
				57290.3225806452,
				[
					[
						"Zoom Camera",
						"0.8",
						""
					]
				]
			],
			[
				59290.3225806452,
				[
					[
						"Add Camera Zoom",
						"",
						""
					]
				]
			],
			[
				59790.3225806452,
				[
					[
						"Add Camera Zoom",
						"",
						""
					]
				]
			],
			[
				60290.3225806452,
				[
					[
						"Add Camera Zoom",
						"",
						""
					]
				]
			],
			[
				60790.3225806452,
				[
					[
						"Add Camera Zoom",
						"",
						""
					]
				]
			],
			[
				61290.3225806452,
				[
					[
						"Add Camera Zoom",
						"",
						""
					]
				]
			],
			[
				61790.3225806452,
				[
					[
						"Add Camera Zoom",
						"",
						""
					]
				]
			],
			[
				62290.3225806452,
				[
					[
						"Add Camera Zoom",
						"",
						""
					]
				]
			],
			[
				62790.3225806452,
				[
					[
						"Add Camera Zoom",
						"",
						""
					]
				]
			],
			[
				63290.3225806452,
				[
					[
						"Add Camera Zoom",
						"",
						""
					]
				]
			],
			[
				63790.3225806452,
				[
					[
						"Add Camera Zoom",
						"",
						""
					]
				]
			],
			[
				64290.3225806452,
				[
					[
						"Add Camera Zoom",
						"",
						""
					]
				]
			],
			[
				64790.3225806452,
				[
					[
						"Add Camera Zoom",
						"",
						""
					]
				]
			],
			[
				65290.3225806452,
				[
					[
						"Add Camera Zoom",
						"",
						""
					]
				]
			],
			[
				65790.3225806452,
				[
					[
						"Add Camera Zoom",
						"",
						""
					]
				]
			],
			[
				66290.3225806452,
				[
					[
						"Add Camera Zoom",
						"",
						""
					]
				]
			],
			[
				66790.3225806452,
				[
					[
						"Add Camera Zoom",
						"",
						""
					]
				]
			],
			[
				67290.3225806452,
				[
					[
						"Add Camera Zoom",
						"",
						""
					]
				]
			],
			[
				67790.3225806452,
				[
					[
						"Add Camera Zoom",
						"",
						""
					]
				]
			],
			[
				68290.3225806452,
				[
					[
						"Add Camera Zoom",
						"",
						""
					]
				]
			],
			[
				68790.3225806452,
				[
					[
						"Add Camera Zoom",
						"",
						""
					]
				]
			],
			[
				69290.3225806452,
				[
					[
						"Add Camera Zoom",
						"",
						""
					]
				]
			],
			[
				69790.3225806452,
				[
					[
						"Add Camera Zoom",
						"",
						""
					]
				]
			],
			[
				70290.3225806452,
				[
					[
						"Add Camera Zoom",
						"",
						""
					]
				]
			],
			[
				70790.3225806452,
				[
					[
						"Add Camera Zoom",
						"",
						""
					]
				]
			],
			[
				71290.3225806452,
				[
					[
						"Add Camera Zoom",
						"",
						""
					]
				]
			],
			[
				71790.3225806452,
				[
					[
						"Add Camera Zoom",
						"",
						""
					]
				]
			],
			[
				72290.3225806452,
				[
					[
						"Add Camera Zoom",
						"",
						""
					]
				]
			],
			[
				72790.3225806452,
				[
					[
						"Add Camera Zoom",
						"",
						""
					]
				]
			],
			[
				73290.3225806452,
				[
					[
						"Add Camera Zoom",
						"",
						""
					]
				]
			],
			[
				73790.3225806452,
				[
					[
						"Add Camera Zoom",
						"",
						""
					]
				]
			],
			[
				74290.3225806452,
				[
					[
						"Add Camera Zoom",
						"",
						""
					]
				]
			],
			[
				74790.3225806452,
				[
					[
						"Add Camera Zoom",
						"",
						""
					]
				]
			],
			[
				75290.3225806452,
				[
					[
						"Add Camera Zoom",
						"",
						""
					]
				]
			],
			[
				75790.3225806452,
				[
					[
						"Add Camera Zoom",
						"",
						""
					]
				]
			],
			[
				76290.3225806452,
				[
					[
						"Add Camera Zoom",
						"",
						""
					]
				]
			],
			[
				76790.3225806452,
				[
					[
						"Add Camera Zoom",
						"",
						""
					]
				]
			],
			[
				77290.3225806452,
				[
					[
						"Add Camera Zoom",
						"",
						""
					]
				]
			],
			[
				77790.3225806452,
				[
					[
						"Add Camera Zoom",
						"",
						""
					]
				]
			],
			[
				78290.3225806452,
				[
					[
						"Add Camera Zoom",
						"",
						""
					]
				]
			],
			[
				78790.3225806452,
				[
					[
						"Add Camera Zoom",
						"",
						""
					]
				]
			],
			[
				79290.3225806452,
				[
					[
						"Add Camera Zoom",
						"",
						""
					]
				]
			],
			[
				79790.3225806452,
				[
					[
						"Add Camera Zoom",
						"",
						""
					]
				]
			],
			[
				80290.3225806452,
				[
					[
						"Add Camera Zoom",
						"",
						""
					]
				]
			],
			[
				80790.3225806452,
				[
					[
						"Add Camera Zoom",
						"",
						""
					]
				]
			],
			[
				81290.3225806452,
				[
					[
						"Add Camera Zoom",
						"",
						""
					]
				]
			],
			[
				81790.3225806452,
				[
					[
						"Add Camera Zoom",
						"",
						""
					]
				]
			],
			[
				82290.3225806452,
				[
					[
						"Add Camera Zoom",
						"",
						""
					]
				]
			],
			[
				82790.3225806452,
				[
					[
						"Add Camera Zoom",
						"",
						""
					]
				]
			],
			[
				83290.3225806452,
				[
					[
						"Add Camera Zoom",
						"",
						""
					]
				]
			],
			[
				83790.3225806452,
				[
					[
						"Add Camera Zoom",
						"",
						""
					]
				]
			],
			[
				84290.3225806452,
				[
					[
						"Add Camera Zoom",
						"",
						""
					]
				]
			],
			[
				84790.3225806452,
				[
					[
						"Add Camera Zoom",
						"",
						""
					]
				]
			],
			[
				85290.3225806452,
				[
					[
						"Add Camera Zoom",
						"",
						""
					]
				]
			],
			[
				85790.3225806452,
				[
					[
						"Add Camera Zoom",
						"",
						""
					]
				]
			],
			[
				86290.3225806452,
				[
					[
						"Add Camera Zoom",
						"",
						""
					]
				]
			],
			[
				86790.3225806452,
				[
					[
						"Add Camera Zoom",
						"",
						""
					]
				]
			],
			[
				87290.3225806452,
				[
					[
						"Add Camera Zoom",
						"",
						""
					]
				]
			],
			[
				87790.3225806452,
				[
					[
						"Add Camera Zoom",
						"",
						""
					]
				]
			],
			[
				88290.3225806452,
				[
					[
						"Add Camera Zoom",
						"",
						""
					]
				]
			],
			[
				88790.3225806452,
				[
					[
						"Add Camera Zoom",
						"",
						""
					]
				]
			],
			[
				89290.3225806452,
				[
					[
						"Add Camera Zoom",
						"",
						""
					]
				]
			],
			[
				89790.3225806452,
				[
					[
						"Add Camera Zoom",
						"",
						""
					]
				]
			],
			[
				90290.3225806452,
				[
					[
						"Add Camera Zoom",
						"",
						""
					]
				]
			],
			[
				90790.3225806452,
				[
					[
						"Add Camera Zoom",
						"",
						""
					]
				]
			],
			[
				91290.3225806452,
				[
					[
						"Zoom Camera",
						"1.0",
						""
					]
				]
			],
			[
				99290.3225806452,
				[
					[
						"Zoom Camera",
						"0.9",
						""
					]
				]
			],
			[
				107290.322580645,
				[
					[
						"Add Camera Zoom",
						"",
						""
					]
				]
			],
			[
				107790.322580645,
				[
					[
						"Add Camera Zoom",
						"",
						""
					]
				]
			],
			[
				108290.322580645,
				[
					[
						"Add Camera Zoom",
						"",
						""
					]
				]
			],
			[
				108790.322580645,
				[
					[
						"Add Camera Zoom",
						"",
						""
					]
				]
			],
			[
				109290.322580645,
				[
					[
						"Add Camera Zoom",
						"",
						""
					]
				]
			],
			[
				109790.322580645,
				[
					[
						"Add Camera Zoom",
						"",
						""
					]
				]
			],
			[
				110290.322580645,
				[
					[
						"Add Camera Zoom",
						"",
						""
					]
				]
			],
			[
				110790.322580645,
				[
					[
						"Add Camera Zoom",
						"",
						""
					]
				]
			],
			[
				111290.322580645,
				[
					[
						"Add Camera Zoom",
						"",
						""
					]
				]
			],
			[
				111790.322580645,
				[
					[
						"Add Camera Zoom",
						"",
						""
					]
				]
			],
			[
				112290.322580645,
				[
					[
						"Add Camera Zoom",
						"",
						""
					]
				]
			],
			[
				112790.322580645,
				[
					[
						"Add Camera Zoom",
						"",
						""
					]
				]
			],
			[
				113290.322580645,
				[
					[
						"Add Camera Zoom",
						"",
						""
					]
				]
			],
			[
				113790.322580645,
				[
					[
						"Add Camera Zoom",
						"",
						""
					]
				]
			],
			[
				114290.322580645,
				[
					[
						"Add Camera Zoom",
						"",
						""
					]
				]
			],
			[
				114790.322580645,
				[
					[
						"Add Camera Zoom",
						"",
						""
					]
				]
			],
			[
				115290.322580645,
				[
					[
						"Add Camera Zoom",
						"",
						""
					]
				]
			],
			[
				115790.322580645,
				[
					[
						"Add Camera Zoom",
						"",
						""
					]
				]
			],
			[
				116290.322580645,
				[
					[
						"Add Camera Zoom",
						"",
						""
					]
				]
			],
			[
				116790.322580645,
				[
					[
						"Add Camera Zoom",
						"",
						""
					]
				]
			],
			[
				117290.322580645,
				[
					[
						"Add Camera Zoom",
						"",
						""
					]
				]
			],
			[
				117790.322580645,
				[
					[
						"Add Camera Zoom",
						"",
						""
					]
				]
			],
			[
				118290.322580645,
				[
					[
						"Add Camera Zoom",
						"",
						""
					]
				]
			],
			[
				118790.322580645,
				[
					[
						"Add Camera Zoom",
						"",
						""
					]
				]
			],
			[
				119290.322580645,
				[
					[
						"Add Camera Zoom",
						"",
						""
					]
				]
			],
			[
				119790.322580645,
				[
					[
						"Add Camera Zoom",
						"",
						""
					]
				]
			],
			[
				120290.322580645,
				[
					[
						"Add Camera Zoom",
						"",
						""
					]
				]
			],
			[
				120790.322580645,
				[
					[
						"Add Camera Zoom",
						"",
						""
					]
				]
			],
			[
				121290.322580645,
				[
					[
						"Add Camera Zoom",
						"",
						""
					]
				]
			],
			[
				121790.322580645,
				[
					[
						"Add Camera Zoom",
						"",
						""
					]
				]
			],
			[
				122290.322580645,
				[
					[
						"Add Camera Zoom",
						"",
						""
					]
				]
			],
			[
				122790.322580645,
				[
					[
						"Add Camera Zoom",
						"",
						""
					]
				]
			],
			[
				123290.322580645,
				[
					[
						"Zoom Camera",
						"0.8",
						""
					]
				]
			],
			[
				126290.322580645,
				[
					[
						"Zoom Camera",
						"0.7",
						""
					],
					[
						"Add Camera Zoom",
						"",
						""
					]
				]
			],
			[
				126665.322580645,
				[
					[
						"Add Camera Zoom",
						"",
						""
					]
				]
			],
			[
				127040.322580645,
				[
					[
						"Add Camera Zoom",
						"",
						""
					]
				]
			],
			[
				127415.322580645,
				[
					[
						"Add Camera Zoom",
						"",
						""
					]
				]
			],
			[
				127790.322580645,
				[
					[
						"Add Camera Zoom",
						"",
						""
					]
				]
			],
			[
				128165.322580645,
				[
					[
						"Add Camera Zoom",
						"",
						""
					]
				]
			],
			[
				128540.322580645,
				[
					[
						"Add Camera Zoom",
						"",
						""
					]
				]
			],
			[
				128915.322580645,
				[
					[
						"Add Camera Zoom",
						"",
						""
					]
				]
			],
			[
				129290.322580645,
				[
					[
						"Add Camera Zoom",
						"",
						""
					]
				]
			],
			[
				129665.322580645,
				[
					[
						"Add Camera Zoom",
						"",
						""
					]
				]
			],
			[
				130040.322580645,
				[
					[
						"Add Camera Zoom",
						"",
						""
					]
				]
			],
			[
				130415.322580645,
				[
					[
						"Add Camera Zoom",
						"",
						""
					]
				]
			],
			[
				130790.322580645,
				[
					[
						"Add Camera Zoom",
						"",
						""
					]
				]
			],
			[
				131165.322580645,
				[
					[
						"Add Camera Zoom",
						"",
						""
					]
				]
			],
			[
				131540.322580645,
				[
					[
						"Add Camera Zoom",
						"",
						""
					]
				]
			],
			[
				131915.322580645,
				[
					[
						"Add Camera Zoom",
						"",
						""
					]
				]
			],
			[
				132290.322580645,
				[
					[
						"Add Camera Zoom",
						"",
						""
					]
				]
			],
			[
				132665.322580645,
				[
					[
						"Add Camera Zoom",
						"",
						""
					]
				]
			],
			[
				133040.322580645,
				[
					[
						"Add Camera Zoom",
						"",
						""
					]
				]
			],
			[
				133415.322580645,
				[
					[
						"Add Camera Zoom",
						"",
						""
					]
				]
			],
			[
				133790.322580645,
				[
					[
						"Add Camera Zoom",
						"",
						""
					]
				]
			],
			[
				134165.322580645,
				[
					[
						"Add Camera Zoom",
						"",
						""
					]
				]
			],
			[
				134540.322580645,
				[
					[
						"Add Camera Zoom",
						"",
						""
					]
				]
			],
			[
				134915.322580645,
				[
					[
						"Add Camera Zoom",
						"",
						""
					]
				]
			],
			[
				135290.322580645,
				[
					[
						"Add Camera Zoom",
						"",
						""
					]
				]
			],
			[
				135665.322580645,
				[
					[
						"Add Camera Zoom",
						"",
						""
					]
				]
			],
			[
				136040.322580645,
				[
					[
						"Add Camera Zoom",
						"",
						""
					]
				]
			],
			[
				136415.322580645,
				[
					[
						"Add Camera Zoom",
						"",
						""
					]
				]
			],
			[
				136790.322580645,
				[
					[
						"Add Camera Zoom",
						"",
						""
					]
				]
			],
			[
				137165.322580645,
				[
					[
						"Add Camera Zoom",
						"",
						""
					]
				]
			],
			[
				137540.322580645,
				[
					[
						"Add Camera Zoom",
						"",
						""
					]
				]
			],
			[
				137915.322580645,
				[
					[
						"Add Camera Zoom",
						"",
						""
					]
				]
			],
			[
				138290.322580645,
				[
					[
						"Add Camera Zoom",
						"",
						""
					]
				]
			],
			[
				138665.322580645,
				[
					[
						"Add Camera Zoom",
						"",
						""
					]
				]
			],
			[
				139040.322580645,
				[
					[
						"Add Camera Zoom",
						"",
						""
					]
				]
			],
			[
				139415.322580645,
				[
					[
						"Add Camera Zoom",
						"",
						""
					]
				]
			],
			[
				139790.322580645,
				[
					[
						"Add Camera Zoom",
						"",
						""
					]
				]
			],
			[
				140165.322580645,
				[
					[
						"Add Camera Zoom",
						"",
						""
					]
				]
			],
			[
				140540.322580645,
				[
					[
						"Add Camera Zoom",
						"",
						""
					]
				]
			],
			[
				140915.322580645,
				[
					[
						"Add Camera Zoom",
						"",
						""
					]
				]
			],
			[
				141290.322580645,
				[
					[
						"Add Camera Zoom",
						"",
						""
					]
				]
			],
			[
				141665.322580645,
				[
					[
						"Add Camera Zoom",
						"",
						""
					]
				]
			],
			[
				142040.322580645,
				[
					[
						"Add Camera Zoom",
						"",
						""
					]
				]
			],
			[
				142415.322580645,
				[
					[
						"Add Camera Zoom",
						"",
						""
					]
				]
			],
			[
				142790.322580645,
				[
					[
						"Add Camera Zoom",
						"",
						""
					]
				]
			],
			[
				143165.322580645,
				[
					[
						"Add Camera Zoom",
						"",
						""
					]
				]
			],
			[
				143540.322580645,
				[
					[
						"Add Camera Zoom",
						"",
						""
					]
				]
			],
			[
				143915.322580645,
				[
					[
						"Add Camera Zoom",
						"",
						""
					]
				]
			],
			[
				144290.322580645,
				[
					[
						"Add Camera Zoom",
						"",
						""
					]
				]
			],
			[
				144665.322580645,
				[
					[
						"Add Camera Zoom",
						"",
						""
					]
				]
			],
			[
				145040.322580645,
				[
					[
						"Add Camera Zoom",
						"",
						""
					]
				]
			],
			[
				145415.322580645,
				[
					[
						"Add Camera Zoom",
						"",
						""
					]
				]
			],
			[
				145790.322580645,
				[
					[
						"Add Camera Zoom",
						"",
						""
					]
				]
			],
			[
				146165.322580645,
				[
					[
						"Add Camera Zoom",
						"",
						""
					]
				]
			],
			[
				146540.322580645,
				[
					[
						"Add Camera Zoom",
						"",
						""
					]
				]
			],
			[
				146915.322580645,
				[
					[
						"Add Camera Zoom",
						"",
						""
					]
				]
			],
			[
				147290.322580645,
				[
					[
						"Add Camera Zoom",
						"",
						""
					]
				]
			],
			[
				147665.322580645,
				[
					[
						"Add Camera Zoom",
						"",
						""
					]
				]
			],
			[
				148040.322580645,
				[
					[
						"Add Camera Zoom",
						"",
						""
					]
				]
			],
			[
				148415.322580645,
				[
					[
						"Add Camera Zoom",
						"",
						""
					]
				]
			],
			[
				148790.322580645,
				[
					[
						"Add Camera Zoom",
						"",
						""
					]
				]
			],
			[
				149165.322580645,
				[
					[
						"Add Camera Zoom",
						"",
						""
					]
				]
			],
			[
				149540.322580645,
				[
					[
						"Add Camera Zoom",
						"",
						""
					]
				]
			],
			[
				149915.322580645,
				[
					[
						"Add Camera Zoom",
						"",
						""
					]
				]
			],
			[
				150290.322580645,
				[
					[
						"Add Camera Zoom",
						"",
						""
					]
				]
			],
			[
				150665.322580645,
				[
					[
						"Add Camera Zoom",
						"",
						""
					]
				]
			],
			[
				151040.322580645,
				[
					[
						"Add Camera Zoom",
						"",
						""
					]
				]
			],
			[
				151415.322580645,
				[
					[
						"Add Camera Zoom",
						"",
						""
					]
				]
			],
			[
				151790.322580645,
				[
					[
						"Add Camera Zoom",
						"",
						""
					]
				]
			],
			[
				152165.322580645,
				[
					[
						"Add Camera Zoom",
						"",
						""
					]
				]
			],
			[
				152540.322580645,
				[
					[
						"Add Camera Zoom",
						"",
						""
					]
				]
			],
			[
				152915.322580645,
				[
					[
						"Add Camera Zoom",
						"",
						""
					]
				]
			],
			[
				153290.322580645,
				[
					[
						"Add Camera Zoom",
						"",
						""
					]
				]
			],
			[
				153665.322580645,
				[
					[
						"Add Camera Zoom",
						"",
						""
					]
				]
			],
			[
				154040.322580645,
				[
					[
						"Add Camera Zoom",
						"",
						""
					]
				]
			],
			[
				154415.322580645,
				[
					[
						"Add Camera Zoom",
						"",
						""
					]
				]
			],
			[
				154790.322580645,
				[
					[
						"Add Camera Zoom",
						"",
						""
					]
				]
			],
			[
				155165.322580645,
				[
					[
						"Add Camera Zoom",
						"",
						""
					]
				]
			],
			[
				155540.322580645,
				[
					[
						"Add Camera Zoom",
						"",
						""
					]
				]
			],
			[
				155915.322580645,
				[
					[
						"Add Camera Zoom",
						"",
						""
					]
				]
			],
			[
				156290.322580645,
				[
					[
						"Add Camera Zoom",
						"",
						""
					]
				]
			],
			[
				156665.322580645,
				[
					[
						"Add Camera Zoom",
						"",
						""
					]
				]
			],
			[
				157040.322580645,
				[
					[
						"Add Camera Zoom",
						"",
						""
					]
				]
			],
			[
				157415.322580645,
				[
					[
						"Add Camera Zoom",
						"",
						""
					]
				]
			],
			[
				157790.322580645,
				[
					[
						"Add Camera Zoom",
						"",
						""
					]
				]
			],
			[
				158165.322580645,
				[
					[
						"Add Camera Zoom",
						"",
						""
					]
				]
			],
			[
				158540.322580645,
				[
					[
						"Add Camera Zoom",
						"",
						""
					]
				]
			],
			[
				158915.322580645,
				[
					[
						"Add Camera Zoom",
						"",
						""
					]
				]
			],
			[
				159290.322580645,
				[
					[
						"Add Camera Zoom",
						"",
						""
					]
				]
			],
			[
				159665.322580645,
				[
					[
						"Add Camera Zoom",
						"",
						""
					]
				]
			],
			[
				160040.322580645,
				[
					[
						"Add Camera Zoom",
						"",
						""
					]
				]
			],
			[
				160415.322580645,
				[
					[
						"Add Camera Zoom",
						"",
						""
					]
				]
			],
			[
				160790.322580645,
				[
					[
						"Add Camera Zoom",
						"",
						""
					]
				]
			],
			[
				161165.322580645,
				[
					[
						"Add Camera Zoom",
						"",
						""
					]
				]
			],
			[
				161540.322580645,
				[
					[
						"Add Camera Zoom",
						"",
						""
					]
				]
			],
			[
				161915.322580645,
				[
					[
						"Add Camera Zoom",
						"",
						""
					]
				]
			],
			[
				163790.322580645,
				[
					[
						"whiteflash",
						"",
						""
					],
					[
						"Zoom Camera",
						"0.8",
						""
					]
				]
			]
		],
		"player3": null,
		"song": "Sweet Dreams",
		"validScore": true,
		"needsVoices": true,
		"stage": "fnaf",
		"speed": 2.3,
		"bpm": 139.5
	}
}
